SOP.v
module tabla_1(input wire A,B,C, output wire Y);

  assign Y = (A & ~B & C) | (A & B & ~C) | (A & B & C);
              
endmodule

SOP_tb.v
module testbench();

reg A, B, C;
wire Y;

tabla_1 U2(A, B, C, Y);

initial begin
  #30
  $display("A B C | Y");
  $display("------|--");
  $monitor("%b %b %b | %b", A, B, C, Y);
     A = 0; B = 0; C = 0;
  #1 A = 0; B = 0; C = 1;
  #1 A = 0; B = 1; C = 0;
  #1 A = 0; B = 1; C = 1;
  #1 A = 1; B = 0; C = 0;
  #1 A = 1; B = 0; C = 1;
  #1 A = 1; B = 1; C = 0;
  #1 A = 1; B = 1; C = 1;
end

initial
  #50 $finish;

initial begin
  $dumpfile("SOP_tb.vcd");
  $dumpvars(0, testbench);
end

endmodule

SOP_tb.vcd
$date
	Sun Aug 09 23:20:42 2020
$end
$version
	Icarus Verilog
$end
$timescale
	1s
$end
$scope module testbench $end
$var wire 1 ! Y $end
$var reg 1 " A $end
$var reg 1 # B $end
$var reg 1 $ C $end
$scope module U2 $end
$var wire 1 " A $end
$var wire 1 # B $end
$var wire 1 $ C $end
$var wire 1 ! Y $end
$upscope $end
$upscope $end
$enddefinitions $end
#0
$dumpvars
x$
x#
x"
x!
$end
#30
0!
0$
0#
0"
#31
1$
#32
0$
1#
#33
1$
#34
0$
0#
1"
#35
1!
1$
#36
0$
1#
#37
1$
